drunkblackjack/__init__.py
drunkblackjack/module.py
drunkblackjack-1.0.5.dist-info/LICENSE
drunkblackjack-1.0.5.dist-info/METADATA
drunkblackjack-1.0.5.dist-info/WHEEL
drunkblackjack-1.0.5.dist-info/top_level.txt
drunkblackjack-1.0.5.dist-info/RECORD
