Metadata-Version: 2.1
Name: drunkblackjack
Version: 1.0.5
Summary: A python package for playing blackjack, with the option to get 'drunk' and see how it affects your play!
Author-email: SWE <ll4725@nyu.edu>
License: GNU GENERAL PUBLIC LICENSE
Keywords: python,package,blackjack
Classifier: Programming Language :: Python :: 3
Classifier: License :: OSI Approved :: GNU General Public License v3 (GPLv3)
Classifier: Operating System :: OS Independent
Requires-Python: >=3.7
License-File: LICENSE
Provides-Extra: dev
Requires-Dist: pytest; extra == "dev"
